cover_generator/__init__.py
cover_generator/color.py
cover_generator/cover_generator.py
cover_generator/font_handling.py
cover_generator/fonts/NotoSerif-Bold.json
cover_generator/fonts/NotoSerif-BoldItalic.json
cover_generator/fonts/__init__.py
cover_generator/fonts/font_width.py
cover_generator/palettes/__init__.py
cover_generator/palettes/palette_generator.py
cover_generator/palettes/DarkColorContrast/DarkColorContrastAnalogous.json
cover_generator/palettes/DarkColorContrast/DarkColorContrastComplimentary.json
cover_generator/palettes/DarkColorContrast/DarkColorContrastTetradic.json
cover_generator/palettes/DarkColorContrast/DarkColorContrastTriadic.json
cover_generator/palettes/DarkColorContrast/__init__.py
cover_generator/palettes/Misc/ColorWhite.json
cover_generator/palettes/Misc/DarkNeon.json
cover_generator/palettes/Misc/__init__.py
cover_generator/palettes/Muted/MutedAnalogous.json
cover_generator/palettes/Muted/MutedComplimentary.json
cover_generator/palettes/Muted/MutedTetradic.json
cover_generator/palettes/Muted/MutedTriadic.json
cover_generator/palettes/Muted/__init__.py
cover_generator/palettes/Pastel/PastelAnalogous.json
cover_generator/palettes/Pastel/PastelComplimentary.json
cover_generator/palettes/Pastel/PastelTetradic.json
cover_generator/palettes/Pastel/PastelTriadic.json
cover_generator/palettes/Pastel/__init__.py
cover_generator/test/__init__.py
cover_generator/test/test_color.py
cover_generator/test/test_cover_generator.py
cover_generator/test/test_font_handling.py
covergenerator-0.2.1.dist-info/licenses/LICENSE
covergenerator-0.2.1.dist-info/METADATA
covergenerator-0.2.1.dist-info/WHEEL
covergenerator-0.2.1.dist-info/entry_points.txt
covergenerator-0.2.1.dist-info/top_level.txt
covergenerator-0.2.1.dist-info/RECORD
