Metadata-Version: 2.4
Name: CoverGenerator
Version: 0.2.1
Summary: Python utility for generating cover images for e-books.
Home-page: https://github.com/Drakovek/CoverGenerator
Author: Drakovek
Author-email: DrakovekMail@gmail.com
Classifier: Programming Language :: Python :: 3
Classifier: License :: OSI Approved :: GNU General Public License v3 (GPLv3)
Classifier: Operating System :: OS Independent
Requires-Python: >=3.8
License-File: LICENSE
Requires-Dist: CairoSVG>=2.5.1
Requires-Dist: HTML-String-Tools>=0.2.0
Requires-Dist: pillow>=8.0.0
Dynamic: author
Dynamic: author-email
Dynamic: classifier
Dynamic: description
Dynamic: description-content-type
Dynamic: home-page
Dynamic: license-file
Dynamic: requires-dist
Dynamic: requires-python
Dynamic: summary
